vtorch/__init__.py
vtorch/common/__init__.py
vtorch/common/checks.py
vtorch/common/loading.py
vtorch/common/persistance.py
vtorch/common/tqdm.py
vtorch/common/utils.py
vtorch/data/__init__.py
vtorch/data/entity.py
vtorch/data/provider.py
vtorch/data/transform.py
vtorch/data/utils.py
vtorch/data/values.py
vtorch/data/iterators/__init__.py
vtorch/data/iterators/base.py
vtorch/data/iterators/batch.py
vtorch/data/iterators/bucket_iterator.py
vtorch/data/iterators/bucket_iterator_iterruptable.py
vtorch/data/iterators/bucket_iterator_optimized.py
vtorch/data/iterators/data_iterator.py
vtorch/data/iterators/interruptable.py
vtorch/data/iterators/length_bs_time.json
vtorch/distillation/__init__.py
vtorch/distillation/model.py
vtorch/distillation/utils.py
vtorch/huggingface/__init__.py
vtorch/huggingface/text.py
vtorch/huggingface/transform.py
vtorch/metrics/__init__.py
vtorch/metrics/fbeta_measure.py
vtorch/metrics/fbeta_measure_with_report.py
vtorch/metrics/metric.py
vtorch/models/__init__.py
vtorch/models/classification.py
vtorch/models/free_lb_model.py
vtorch/models/model.py
vtorch/models/multitask_classification.py
vtorch/nn/__init__.py
vtorch/nn/packed_sequence.py
vtorch/nn/utils.py
vtorch/nn/layers/__init__.py
vtorch/nn/layers/aggregation.py
vtorch/nn/layers/attention.py
vtorch/nn/layers/pooling.py
vtorch/nn/layers/spacial_dropout.py
vtorch/nn/layers/rnn/__init__.py
vtorch/nn/layers/rnn/gru.py
vtorch/nn/layers/rnn/lstm.py
vtorch/nn/layers/rnn/rnn_layer.py
vtorch/nn/layers/rnn/vanila_rnn.py
vtorch/nn/losses/__init__.py
vtorch/nn/losses/losses.py
vtorch/postprocessing/__init__.py
vtorch/postprocessing/default.py
vtorch/postprocessing/multiclass.py
vtorch/postprocessing/multilabel.py
vtorch/predictors/__init__.py
vtorch/predictors/model.py
vtorch/predictors/multiclass.py
vtorch/predictors/multiclass_provider.py
vtorch/predictors/multilabel.py
vtorch/predictors/multilabel_provider.py
vtorch/predictors/utils.py
vtorch/training/__init__.py
vtorch-1.4.8.dist-info/METADATA
vtorch-1.4.8.dist-info/WHEEL
vtorch-1.4.8.dist-info/top_level.txt
vtorch-1.4.8.dist-info/RECORD
